LICENSE
MANIFEST.in
README.md
setup.cfg
setup.py
docassemble/__init__.py
docassemble.EC.egg-info/PKG-INFO
docassemble.EC.egg-info/SOURCES.txt
docassemble.EC.egg-info/dependency_links.txt
docassemble.EC.egg-info/namespace_packages.txt
docassemble.EC.egg-info/not-zip-safe
docassemble.EC.egg-info/top_level.txt
docassemble/EC/__init__.py
docassemble/EC/data/questions/employment.yml
docassemble/EC/data/sources/README.md
docassemble/EC/data/static/README.md
docassemble/EC/data/templates/ECsample.docx
docassemble/EC/data/templates/README.md